.pre-commit-config.yaml
AUTHORS.md
LICENSE.md
MANIFEST.in
README.md
noxfile.py
pyproject.toml
requirements-development.txt
requirements-testing.txt
requirements.txt
setup.cfg
setup.py
barrier3d/__init__.py
barrier3d/_version.py
barrier3d/barrier3d.py
barrier3d/bmi.py
barrier3d/cli.py
barrier3d/configuration.py
barrier3d/load_input.py
barrier3d.egg-info/PKG-INFO
barrier3d.egg-info/SOURCES.txt
barrier3d.egg-info/dependency_links.txt
barrier3d.egg-info/entry_points.txt
barrier3d.egg-info/requires.txt
barrier3d.egg-info/top_level.txt
barrier3d/data/barrier3d-default-dunes.csv
barrier3d/data/barrier3d-default-elevations.csv
barrier3d/data/barrier3d-default-growthparam.csv
barrier3d/data/barrier3d-default-storms.csv
barrier3d/tools/__init__.py
barrier3d/tools/input_files.py
barrier3d/tools/plot.py
scripts/plot_BMI_vs_V1.py
scripts/runB3D_BMI.py
scripts/runB3D_V1.py
tests/test_params.py
tests/test_versions.py
tests/test_params/VCRStormList.npy
tests/test_params/barrier3d-default-dunes.npy
tests/test_params/barrier3d-default-elevations.npy
tests/test_params/barrier3d-default-growthparam.npy
tests/test_params/barrier3d-default-parameters.py
tests/test_params/barrier3d-default-parameters.yaml
tests/test_params/barrier3d-default-storms.npy
tests/test_params/OLD/DuneStart_1000dam.npy
tests/test_params/OLD/InitElevHog.npy
tests/test_params/OLD/StormTimeSeries_1000yr.npy
tests/test_params/OLD/barrier3d-storms.npy
tests/test_params/OLD/barrier3d.xlsx
tests/test_params/OLD/growthparam_1000dam.npy
tests/test_versions/DuneStart_1000dam.npy
tests/test_versions/InitElevHog.npy
tests/test_versions/README.md
tests/test_versions/StormTimeSeries_1000yr.npy
tests/test_versions/barrier3d-default-parameters.yaml
tests/test_versions/growthparam_1000dam.npy
tests/test_versions/license.txt