Metadata-Version: 2.1
Name: barrier3d
Version: 2.0.1
Summary: A spatially explicit exploratory model of barrier island evolution
Author: Ian Reeves
Author-email: ian.reeves@whoi.edu
Maintainer: Ian Reeves
Maintainer-email: ian.reeves@whoi.edu
License: ### GNU GENERAL PUBLIC LICENSE
Project-URL: homepage, https://github.com/UNC-CECL/Barrier3D
Project-URL: documentation, https://github.com/UNC-CECL/Barrier3D
Project-URL: repository, https://github.com/UNC-CECL/Barrier3D
Project-URL: changelog, https://raw.githubusercontent.com/UNC-CECL/Barrier3D/master/CHANGES.rst
Keywords: earth science,coast,barrier island
Classifier: Development Status :: 4 - Beta
Classifier: Intended Audience :: Science/Research
Classifier: License :: OSI Approved :: MIT License
Classifier: Operating System :: OS Independent
Classifier: Programming Language :: Python :: 3
Classifier: Programming Language :: Python :: 3.8
Classifier: Programming Language :: Python :: 3.9
Classifier: Programming Language :: Python :: 3.10
Classifier: Programming Language :: Python :: 3.11
Classifier: Programming Language :: Python :: 3 :: Only
Classifier: Topic :: Scientific/Engineering :: Physics
Requires-Python: >=3.8
Provides-Extra: dev
License-File: LICENSE.md
License-File: AUTHORS.md
